diffable/__init__.py
diffable/models.py
django_diffable-1.0.0.dist-info/LICENSE
django_diffable-1.0.0.dist-info/METADATA
django_diffable-1.0.0.dist-info/WHEEL
django_diffable-1.0.0.dist-info/top_level.txt
django_diffable-1.0.0.dist-info/RECORD
